MANIFEST.in
README.md
setup.py
django_tinymce_images.egg-info/PKG-INFO
django_tinymce_images.egg-info/SOURCES.txt
django_tinymce_images.egg-info/dependency_links.txt
django_tinymce_images.egg-info/not-zip-safe
django_tinymce_images.egg-info/requires.txt
django_tinymce_images.egg-info/top_level.txt
tinymce_images/__init__.py
tinymce_images/urls.py
tinymce_images/views.py
tinymce_images/views_old.py
tinymce_images/static/tiny_mce/plugins/images/editor_plugin.js
tinymce_images/static/tiny_mce/plugins/images/editor_plugin_src.js
tinymce_images/static/tiny_mce/plugins/images/images.html
tinymce_images/static/tiny_mce/plugins/images/readme.html
tinymce_images/static/tiny_mce/plugins/images/css/images.css
tinymce_images/static/tiny_mce/plugins/images/img/addrBack.gif
tinymce_images/static/tiny_mce/plugins/images/img/addrLeft.gif
tinymce_images/static/tiny_mce/plugins/images/img/addrRight.gif
tinymce_images/static/tiny_mce/plugins/images/img/ajax-loader-files.gif
tinymce_images/static/tiny_mce/plugins/images/img/ajax-loader.gif
tinymce_images/static/tiny_mce/plugins/images/img/arrowRight.gif
tinymce_images/static/tiny_mce/plugins/images/img/backActive.gif
tinymce_images/static/tiny_mce/plugins/images/img/backDisabled.gif
tinymce_images/static/tiny_mce/plugins/images/img/backEnabled.gif
tinymce_images/static/tiny_mce/plugins/images/img/cancelbutton.gif
tinymce_images/static/tiny_mce/plugins/images/img/chain.png
tinymce_images/static/tiny_mce/plugins/images/img/chain_small.png
tinymce_images/static/tiny_mce/plugins/images/img/cross_circle_frame.png
tinymce_images/static/tiny_mce/plugins/images/img/cross_small.png
tinymce_images/static/tiny_mce/plugins/images/img/folder.png
tinymce_images/static/tiny_mce/plugins/images/img/folder_arrow.png
tinymce_images/static/tiny_mce/plugins/images/img/folder_minus.png
tinymce_images/static/tiny_mce/plugins/images/img/folder_open.png
tinymce_images/static/tiny_mce/plugins/images/img/folder_open_document.png
tinymce_images/static/tiny_mce/plugins/images/img/folder_open_image.png
tinymce_images/static/tiny_mce/plugins/images/img/folder_plus.png
tinymce_images/static/tiny_mce/plugins/images/img/folders.png
tinymce_images/static/tiny_mce/plugins/images/img/footBackground.gif
